{
  "id": "aitareya",
  "name": "Aitareya Upanishad",
  "name_sanskrit": "ऐतरेयोपनिषद्",
  "tradition": "Rigveda",
  "summary": "The Aitareya Upanishad from the Rigveda describes the creation of the universe from the Self, the creation of the human being, and ultimately declares that consciousness (prajna) is Brahman — prajnanam brahma.",
  "total_verses": 33,
  "verses": [
    {
      "upanishad": "aitareya",
      "verse_number": 1,
      "tags": [
        "creation",
        "Atman",
        "Self",
        "universe"
      ],
      "sanskrit": "आत्मा वा इदमेक एवाग्र आसीत् | नान्यत् किञ्चन मिषत् |\nस ईक्षत लोकान्नु सृजा इति ||१.१.१||",
      "transliteration": "ātmā vā idam eka evāgra āsīt | nānyat kiñcana miṣat |\nsa īkṣata lokān nu sṛjā iti ||1.1.1||",
      "word_meanings": [
        {
          "word": "आत्मा एकः एव",
          "meaning": "the Self alone"
        },
        {
          "word": "अग्रे आसीत्",
          "meaning": "existed in the beginning"
        },
        {
          "word": "नान्यत् किञ्चन",
          "meaning": "nothing else whatsoever"
        },
        {
          "word": "मिषत्",
          "meaning": "that blinked/existed"
        },
        {
          "word": "ईक्षत",
          "meaning": "he thought/willed"
        },
        {
          "word": "लोकान् सृजा",
          "meaning": "let me create worlds"
        }
      ],
      "english_translation": "In the beginning, the Self alone existed here — nothing else whatsoever blinked. He thought: 'Let me create worlds.'",
      "shankara_bhashya_sanskrit": "आत्मा — परमात्मा — एकः एव अग्रे आसीत्। सृष्टेः पूर्वम् आत्मा एव आसीत्। स ईक्षत — संकल्पं कृतवान् — लोकान् सृजामि इति।",
      "shankara_bhashya_english": "Shankara: Before creation, the supreme Self alone existed. Nothing else — no world, no beings. The Self willed to create worlds. This shows that creation proceeds from the Self's own will, not from any external material."
    },
    {
      "upanishad": "aitareya",
      "verse_number": 2,
      "tags": [
        "consciousness",
        "Brahman",
        "prajnanam",
        "mahavakya"
      ],
      "sanskrit": "प्रज्ञानं ब्रह्म ||३.१.३||",
      "transliteration": "prajñānaṃ brahma ||3.1.3||",
      "word_meanings": [
        {
          "word": "प्रज्ञानम्",
          "meaning": "consciousness, pure awareness"
        },
        {
          "word": "ब्रह्म",
          "meaning": "is Brahman"
        }
      ],
      "english_translation": "Consciousness is Brahman.",
      "shankara_bhashya_sanskrit": "प्रज्ञानम् — विशुद्धं चैतन्यम् — ब्रह्म। इदम् महावाक्यम् — जीवब्रह्मैक्यं बोधयति।",
      "shankara_bhashya_english": "Shankara: Pure consciousness is Brahman. This is one of the four great sayings (mahavakyas) of the Upanishads, from the Rigveda. It declares the identity of the individual consciousness with the supreme Brahman."
    },
    {
      "upanishad": "aitareya",
      "verse_number": 3,
      "tags": [
        "consciousness",
        "all beings",
        "Brahman"
      ],
      "sanskrit": "प्रज्ञेनैव पश्यति प्रज्ञेन शृणोति | प्रज्ञेन गन्धान् जिघ्रति प्रज्ञेन वाचं वदति |\nप्रज्ञेन प्रियाप्रिये विजानाति ||३.१.२||",
      "transliteration": "prajñenaiva paśyati prajñena śṛṇoti | prajñena gandhān jighrati prajñena vācaṃ vadati |\nprajñena priyāpriye vijānāti ||3.1.2||",
      "word_meanings": [
        {
          "word": "प्रज्ञेन पश्यति",
          "meaning": "by consciousness one sees"
        },
        {
          "word": "प्रज्ञेन शृणोति",
          "meaning": "by consciousness one hears"
        },
        {
          "word": "प्रज्ञेन वदति",
          "meaning": "by consciousness one speaks"
        },
        {
          "word": "प्रियाप्रिये विजानाति",
          "meaning": "knows the pleasant and unpleasant"
        }
      ],
      "english_translation": "By consciousness alone one sees, by consciousness one hears, by consciousness one smells fragrances, by consciousness one speaks, by consciousness one knows the pleasant and unpleasant.",
      "shankara_bhashya_sanskrit": "प्रज्ञेन — चैतन्येन — सर्वाणि इन्द्रियाणि प्रवर्तन्ते। चैतन्यम् एव सर्वस्य प्रवर्तकम्।",
      "shankara_bhashya_english": "Shankara: All the senses function by consciousness alone. Consciousness is the activator of everything. Without consciousness, no sense organ can function. This leads to the conclusion: consciousness (prajna) is Brahman."
    },
    {
      "upanishad": "aitareya",
      "verse_number": 4,
      "tags": [
        "creation",
        "waters",
        "Brahman",
        "cosmic egg"
      ],
      "sanskrit": "स ईक्षत इमे नु लोका लोकपालान्नु सृजा इति | सोऽद्भ्य एव पुरुषमुद्धृत्य अमूर्च्छयत् ||१.१.३||",
      "transliteration": "sa īkṣata ime nu lokā lokapālān nu sṛjā iti | so'dbhya eva puruṣam uddhṛtya amūrcchayat ||1.1.3||",
      "word_meanings": [
        {
          "word": "लोकपालान् सृजा",
          "meaning": "let me create guardians of the worlds"
        },
        {
          "word": "अद्भ्यः पुरुषम् उद्धृत्य",
          "meaning": "drawing a person from the waters"
        },
        {
          "word": "अमूर्च्छयत्",
          "meaning": "gave it form"
        }
      ],
      "english_translation": "He thought: 'These are the worlds. Let me create guardians of the worlds.' He drew a person from the waters and gave it form.",
      "shankara_bhashya_sanskrit": "लोकपालान् — लोकानां पालकान् — सृजामि इति ईक्षत। अद्भ्यः पुरुषम् उद्धृत्य — जलात् पुरुषाकारम् उद्धृत्य — अमूर्च्छयत् — मूर्तिमत् अकरोत्।",
      "shankara_bhashya_english": "Shankara: Having created the worlds, the Self thought to create guardians for them. It drew a cosmic person from the primordial waters and gave it form — this is the creation of the cosmic body (virat)."
    },
    {
      "upanishad": "aitareya",
      "verse_number": 5,
      "tags": [
        "senses",
        "creation",
        "hunger",
        "thirst"
      ],
      "sanskrit": "तं तपस्तप्त्वा मुखं निरभिद्यत यथाण्डं मुखाद्वाग्वाचोऽग्निः ||१.१.४||",
      "transliteration": "taṃ tapas taptva mukhaṃ nirabhidyata yathāṇḍaṃ mukhād vāg vāco'gniḥ ||1.1.4||",
      "word_meanings": [
        {
          "word": "तपः तप्त्वा",
          "meaning": "having brooded/heated"
        },
        {
          "word": "मुखम् निरभिद्यत",
          "meaning": "the mouth burst open"
        },
        {
          "word": "वाक्",
          "meaning": "speech"
        },
        {
          "word": "अग्निः",
          "meaning": "fire (deity of speech)"
        }
      ],
      "english_translation": "Having brooded over it, the mouth burst open as an egg bursts. From the mouth came speech; from speech, fire.",
      "shankara_bhashya_sanskrit": "तपः तप्त्वा — ऊष्मणा — मुखम् निरभिद्यत। मुखात् वाक् — वाचः अग्निः — वाग्देवता अग्निः।",
      "shankara_bhashya_english": "Shankara: Through the heat of brooding (tapas), the cosmic body's organs burst open. From the mouth came speech, and the deity of speech is Agni (fire). This describes the cosmic origin of the organs of action."
    },
    {
      "upanishad": "aitareya",
      "verse_number": 6,
      "tags": [
        "Atman",
        "entered",
        "body",
        "hunger"
      ],
      "sanskrit": "ता एता देवताः सृष्टा अस्मिन्महत्यर्णवे प्रापतन् | तमशनायापिपासाभ्यामन्ववार्जत् ||१.२.१||",
      "transliteration": "tā etā devatāḥ sṛṣṭā asmin mahaty arṇave prāpatan | tam aśanāyāpipāsābhyām anvavārjat ||1.2.1||",
      "word_meanings": [
        {
          "word": "देवताः सृष्टाः",
          "meaning": "the created deities"
        },
        {
          "word": "महति अर्णवे प्रापतन्",
          "meaning": "fell into the great ocean"
        },
        {
          "word": "अशनाया अपिपासाभ्याम्",
          "meaning": "by hunger and thirst"
        },
        {
          "word": "अन्ववार्जत्",
          "meaning": "were overcome"
        }
      ],
      "english_translation": "These created deities fell into the great ocean. Hunger and thirst overcame him (the cosmic person).",
      "shankara_bhashya_sanskrit": "देवताः — वाग्आदयः — अस्मिन् महति अर्णवे — संसारसागरे — प्रापतन्। अशनाया अपिपासाभ्याम् — क्षुत्पिपासाभ्याम् — अन्ववार्जत्।",
      "shankara_bhashya_english": "Shankara: The created deities (speech, etc.) fell into the great ocean of samsara. The cosmic person was overcome by hunger and thirst — the fundamental drives that sustain embodied existence."
    },
    {
      "upanishad": "aitareya",
      "verse_number": 7,
      "tags": [
        "Atman",
        "entered body",
        "food",
        "anna"
      ],
      "sanskrit": "सोऽकामयत | अन्नं मे सृज्यतामिति | स एतं रश्मिमभ्यतपत् | तस्माद्रश्मितप्तात् अन्नमजायत ||१.३.१||",
      "transliteration": "so'kāmayata | annaṃ me sṛjyatām iti | sa etaṃ raśmim abhyatapat | tasmād raśmitaptāt annam ajāyata ||1.3.1||",
      "word_meanings": [
        {
          "word": "अन्नम् सृज्यताम्",
          "meaning": "let food be created for me"
        },
        {
          "word": "रश्मिम् अभ्यतपत्",
          "meaning": "brooded over this ray"
        },
        {
          "word": "अन्नम् अजायत",
          "meaning": "food was born"
        }
      ],
      "english_translation": "He desired: 'Let food be created for me.' He brooded over this ray. From that brooded-upon ray, food was born.",
      "shankara_bhashya_sanskrit": "अन्नम् — भोज्यम् — सृज्यताम् इति अकामयत। रश्मिम् अभ्यतपत् — सूर्यरश्मिम् ध्यात्वा — अन्नम् अजायत।",
      "shankara_bhashya_english": "Shankara: The Self desired food for the cosmic person. By brooding over the solar ray, food (the material world) was created. This describes the creation of the objective world as food for the subjective Self."
    },
    {
      "upanishad": "aitareya",
      "verse_number": 8,
      "tags": [
        "Atman",
        "entered",
        "body",
        "three births"
      ],
      "sanskrit": "स एतमेव सीमानं विदार्यैतया द्वारा प्रापद्यत | सैषा विदृतिर्नाम द्वास्तदेतन्नान्दनं नाम ||१.३.१२||",
      "transliteration": "sa etam eva sīmānam vidāryaitayā dvārā prāpadyata | saiṣā vidṛtir nāma dvās tad etan nāndanaṃ nāma ||1.3.12||",
      "word_meanings": [
        {
          "word": "सीमानम् विदार्य",
          "meaning": "splitting the crown of the head"
        },
        {
          "word": "एतया द्वारा",
          "meaning": "by this door"
        },
        {
          "word": "विदृतिः नाम द्वाः",
          "meaning": "the door called Vidrti (the cleft)"
        },
        {
          "word": "नान्दनम् नाम",
          "meaning": "called Nandana (the place of joy)"
        }
      ],
      "english_translation": "Splitting the crown of the head, it entered by this door. This door is called Vidrti (the cleft). This is the place called Nandana (joy).",
      "shankara_bhashya_sanskrit": "सीमानम् विदार्य — ब्रह्मरन्ध्रम् भित्त्वा — प्रविशत्। विदृतिः — ब्रह्मरन्ध्रम् — नान्दनम् — आनन्दस्थानम्।",
      "shankara_bhashya_english": "Shankara: The Self entered the cosmic body through the crown of the head (brahmarandhra). This is called Vidrti (the cleft) and Nandana (the place of joy) — because the Self's entry brings consciousness and bliss to the body."
    },
    {
      "upanishad": "aitareya",
      "verse_number": 9,
      "tags": [
        "three births",
        "first birth",
        "womb",
        "Self"
      ],
      "sanskrit": "स जातो भूतान्यभिव्यैख्यत् | किमिहान्यं वावदिषदिति | स एतमेव पुरुषं ब्रह्म ततममपश्यत् | इदमदर्शमिति ||२.१.१||",
      "transliteration": "sa jāto bhūtāny abhivyaikhyat | kim ihānyaṃ vāvadiṣad iti | sa etam eva puruṣaṃ brahma tatamam apaśyat | idam adarśam iti ||2.1.1||",
      "word_meanings": [
        {
          "word": "जातः",
          "meaning": "having been born"
        },
        {
          "word": "भूतानि अभिव्यैख्यत्",
          "meaning": "looked upon all beings"
        },
        {
          "word": "ब्रह्म ततमम्",
          "meaning": "Brahman spread everywhere"
        },
        {
          "word": "इदम् अदर्शम्",
          "meaning": "I have seen this"
        }
      ],
      "english_translation": "Having been born, he looked upon all beings. What else would he have wished to speak? He saw this very Brahman spread everywhere. 'I have seen this,' he said.",
      "shankara_bhashya_sanskrit": "जातः — जन्म प्राप्य — भूतानि अभिव्यैख्यत् — सर्वाणि भूतानि अपश्यत्। ब्रह्म ततमम् — सर्वत्र व्याप्तम् ब्रह्म — अपश्यत्।",
      "shankara_bhashya_english": "Shankara: At birth, the wise one looked upon all beings and saw Brahman spread everywhere. 'I have seen this' — this is the vision of the knower who recognizes Brahman in all beings at the very moment of birth."
    },
    {
      "upanishad": "aitareya",
      "verse_number": 10,
      "tags": [
        "prajnanam",
        "Brahman",
        "mahavakya",
        "consciousness"
      ],
      "sanskrit": "प्रज्ञानेत्रश्च लोकः प्रज्ञाने प्रतिष्ठितः | प्रज्ञानेत्रं ब्रह्म | प्रज्ञानं ब्रह्म ||३.१.३||",
      "transliteration": "prajñānetras ca lokaḥ prajñāne pratiṣṭhitaḥ | prajñānetraṃ brahma | prajñānaṃ brahma ||3.1.3||",
      "word_meanings": [
        {
          "word": "प्रज्ञानेत्रः लोकः",
          "meaning": "the world has consciousness as its eye"
        },
        {
          "word": "प्रज्ञाने प्रतिष्ठितः",
          "meaning": "established in consciousness"
        },
        {
          "word": "प्रज्ञानेत्रम् ब्रह्म",
          "meaning": "Brahman has consciousness as its eye"
        },
        {
          "word": "प्रज्ञानम् ब्रह्म",
          "meaning": "consciousness is Brahman"
        }
      ],
      "english_translation": "The world has consciousness as its eye and is established in consciousness. Brahman has consciousness as its eye. Consciousness is Brahman.",
      "shankara_bhashya_sanskrit": "प्रज्ञानेत्रः लोकः — प्रज्ञानम् नेत्रम् यस्य — चैतन्यम् यस्य दृष्टिः। प्रज्ञानम् ब्रह्म — चैतन्यम् एव ब्रह्म।",
      "shankara_bhashya_english": "Shankara: The world has consciousness as its eye — it is seen and known through consciousness. Brahman itself has consciousness as its eye — Brahman is pure consciousness. Therefore: consciousness is Brahman. This is the mahavakya of the Rigveda."
    },
    {
      "upanishad": "aitareya",
      "verse_number": 11,
      "tags": [
        "creation",
        "waters",
        "fire",
        "earth"
      ],
      "sanskrit": "स ईक्षत इमे नु लोका लोकपालान्नु सृजा इति | सोऽद्भ्य एव पुरुषमुद्धृत्य अमूर्च्छयत् ||१.१.३||",
      "transliteration": "sa īkṣata ime nu lokā lokapālān nu sṛjā iti | so'dbhya eva puruṣam uddhṛtya amūrcchayat ||1.1.3||",
      "word_meanings": [
        {
          "word": "लोकपालान् सृजा",
          "meaning": "let me create guardians of the worlds"
        },
        {
          "word": "अद्भ्यः पुरुषम् उद्धृत्य",
          "meaning": "drawing a person from the waters"
        },
        {
          "word": "अमूर्च्छयत्",
          "meaning": "gave it form"
        }
      ],
      "english_translation": "He thought: 'These are the worlds. Let me create guardians of the worlds.' He drew a person from the waters and gave it form.",
      "shankara_bhashya_sanskrit": "लोकपालान् — लोकानां पालकान् — सृजामि इति ईक्षत। अद्भ्यः पुरुषम् उद्धृत्य — जलात् पुरुषाकारम् उद्धृत्य — अमूर्च्छयत्।",
      "shankara_bhashya_english": "Shankara: Having created the worlds, the Self thought to create guardians for them. It drew a cosmic person from the primordial waters and gave it form — this is the creation of the cosmic body (virat)."
    },
    {
      "upanishad": "aitareya",
      "verse_number": 12,
      "tags": [
        "organs",
        "deities",
        "fire",
        "Agni",
        "Vayu"
      ],
      "sanskrit": "नासिके प्राणमसृजत | तस्माद्वायुः | नेत्रे चक्षुरसृजत | तस्मादादित्यः ||१.१.४||",
      "transliteration": "nāsike prāṇam asṛjat | tasmād vāyuḥ | netre cakṣur asṛjat | tasmād ādityaḥ ||1.1.4||",
      "word_meanings": [
        {
          "word": "नासिके प्राणम् असृजत",
          "meaning": "from the nostrils he created prana"
        },
        {
          "word": "तस्मात् वायुः",
          "meaning": "from that, Vayu (wind)"
        },
        {
          "word": "नेत्रे चक्षुः असृजत",
          "meaning": "from the eyes he created sight"
        },
        {
          "word": "तस्मात् आदित्यः",
          "meaning": "from that, the Sun"
        }
      ],
      "english_translation": "From the nostrils he created prana — from that, Vayu. From the eyes he created sight — from that, the Sun.",
      "shankara_bhashya_sanskrit": "नासिकाभ्याम् प्राणः — वायुः। नेत्राभ्याम् चक्षुः — आदित्यः। प्रत्येकम् इन्द्रियात् देवता।",
      "shankara_bhashya_english": "Shankara: Each sense organ has a corresponding cosmic deity. From the nostrils/prana came Vayu (wind); from the eyes/sight came the Sun. This shows the correspondence between the microcosm (individual body) and the macrocosm (universe)."
    },
    {
      "upanishad": "aitareya",
      "verse_number": 13,
      "tags": [
        "hunger",
        "food",
        "anna",
        "creation",
        "body"
      ],
      "sanskrit": "तमशनायापिपासे अभ्यवर्तेताम् | सोऽकामयत | अन्नं मे सृज्यतामिति ||१.२.१||",
      "transliteration": "tam aśanāyāpipāse abhyavartetām | so'kāmayata | annaṃ me sṛjyatām iti ||1.2.1||",
      "word_meanings": [
        {
          "word": "अशनाया अपिपासे",
          "meaning": "hunger and thirst"
        },
        {
          "word": "अभ्यवर्तेताम्",
          "meaning": "approached him"
        },
        {
          "word": "अन्नम् सृज्यताम्",
          "meaning": "let food be created"
        }
      ],
      "english_translation": "Hunger and thirst approached him. He desired: 'Let food be created for me.'",
      "shankara_bhashya_sanskrit": "अशनाया — क्षुत् — अपिपासा — तृष्णा — तम् अभ्यवर्तेताम्। सः अकामयत — अन्नम् सृज्यताम्।",
      "shankara_bhashya_english": "Shankara: The cosmic person experienced hunger and thirst — the fundamental drives of embodied existence. He desired food to be created. This describes the creation of the objective world as the food for the subjective Self."
    },
    {
      "upanishad": "aitareya",
      "verse_number": 14,
      "tags": [
        "Self",
        "entered body",
        "three births",
        "womb"
      ],
      "sanskrit": "तान्येतानि कर्माणि सत्यानि | अथ खल्वेतानि कर्माणि सत्यानि | अथ खल्वेतानि कर्माणि सत्यानि ||२.१.१||",
      "transliteration": "tāny etāni karmāṇi satyāni | atha khalv etāni karmāṇi satyāni | atha khalv etāni karmāṇi satyāni ||2.1.1||",
      "word_meanings": [
        {
          "word": "एतानि कर्माणि सत्यानि",
          "meaning": "these actions are true/real"
        },
        {
          "word": "अथ खलु",
          "meaning": "now indeed"
        }
      ],
      "english_translation": "These actions are indeed real. Now indeed these actions are real. Now indeed these actions are real.",
      "shankara_bhashya_sanskrit": "एतानि कर्माणि — सृष्टिकर्माणि — सत्यानि — वास्तवानि। त्रिवारम् उक्तम् — दृढीकरणाय।",
      "shankara_bhashya_english": "Shankara: The acts of creation are real — not illusory. The threefold repetition emphasizes the reality of the creative process. This prepares for the teaching about the three births of the Self."
    },
    {
      "upanishad": "aitareya",
      "verse_number": 15,
      "tags": [
        "three births",
        "first birth",
        "conception",
        "Self"
      ],
      "sanskrit": "गर्भो ह वा अयमस्मिन् रेतः सिच्यते | तदेतत्सर्वाङ्गेभ्यस्तेजः समभरत् | तन्नारीमेव गच्छति ||२.१.३||",
      "transliteration": "garbho ha vā ayam asmin retaḥ sicyate | tad etat sarvāṅgebhyas tejaḥ samabharat | tan nārīm eva gacchati ||2.1.3||",
      "word_meanings": [
        {
          "word": "गर्भः",
          "meaning": "the embryo"
        },
        {
          "word": "रेतः सिच्यते",
          "meaning": "seed is sown"
        },
        {
          "word": "सर्वाङ्गेभ्यः तेजः",
          "meaning": "vitality from all limbs"
        },
        {
          "word": "नारीम् गच्छति",
          "meaning": "goes to the woman"
        }
      ],
      "english_translation": "This is the first birth: the seed is sown in him. That vitality gathered from all limbs goes to the woman.",
      "shankara_bhashya_sanskrit": "प्रथमम् जन्म — गर्भाधानम्। रेतः — बीजम् — नारीम् गच्छति।",
      "shankara_bhashya_english": "Shankara: The first birth is conception — when the seed (carrying the Self) is sown. The vitality gathered from all limbs of the father goes to the mother. This is the beginning of the Self's journey into a new body."
    },
    {
      "upanishad": "aitareya",
      "verse_number": 16,
      "tags": [
        "second birth",
        "birth from womb",
        "Self",
        "mother"
      ],
      "sanskrit": "स जायमानो यं लोकं जायते तेन सम्भवति | स एव तस्य द्वितीयं जन्म ||२.१.४||",
      "transliteration": "sa jāyamāno yaṃ lokaṃ jāyate tena sambhavati | sa eva tasya dvitīyaṃ janma ||2.1.4||",
      "word_meanings": [
        {
          "word": "जायमानः",
          "meaning": "being born"
        },
        {
          "word": "यम् लोकम् जायते",
          "meaning": "the world into which he is born"
        },
        {
          "word": "तेन सम्भवति",
          "meaning": "he comes into being through it"
        },
        {
          "word": "द्वितीयम् जन्म",
          "meaning": "the second birth"
        }
      ],
      "english_translation": "Being born, he comes into being through the world into which he is born. That is his second birth.",
      "shankara_bhashya_sanskrit": "द्वितीयम् जन्म — मातुः गर्भात् जन्म। यम् लोकम् जायते — यस्मिन् लोके जन्म प्राप्नोति।",
      "shankara_bhashya_english": "Shankara: The second birth is physical birth from the mother's womb. The Self comes into the world and takes on a new identity. This is the birth that most people consider the only birth."
    },
    {
      "upanishad": "aitareya",
      "verse_number": 17,
      "tags": [
        "third birth",
        "death",
        "liberation",
        "Self"
      ],
      "sanskrit": "तस्य प्रेतस्य यं लोकं प्रेष्यन्ति | तस्मात्सम्भवति | तत्तृतीयं जन्म ||२.१.५||",
      "transliteration": "tasya pretasya yaṃ lokaṃ preṣyanti | tasmāt sambhavati | tat tṛtīyaṃ janma ||2.1.5||",
      "word_meanings": [
        {
          "word": "प्रेतस्य",
          "meaning": "of the departed (dead)"
        },
        {
          "word": "यम् लोकम् प्रेष्यन्ति",
          "meaning": "the world to which they send him"
        },
        {
          "word": "तृतीयम् जन्म",
          "meaning": "the third birth"
        }
      ],
      "english_translation": "Of the departed, the world to which they send him — from that he comes into being. That is the third birth.",
      "shankara_bhashya_sanskrit": "तृतीयम् जन्म — मृत्योः परम् — परलोके जन्म। प्रेतस्य — मृतस्य — यम् लोकम् प्रेष्यन्ति — तस्मात् सम्भवति।",
      "shankara_bhashya_english": "Shankara: The third birth is after death — the rebirth in another world or another body. The Aitareya teaches that the Self undergoes three births: conception, physical birth, and rebirth after death. Liberation means transcending all three births."
    },
    {
      "upanishad": "aitareya",
      "verse_number": 18,
      "tags": [
        "Vamadeva",
        "womb",
        "liberation",
        "knowledge"
      ],
      "sanskrit": "तदुक्तमृषिणा | गर्भे नु सन्नन्वेषामवेदमहं देवानां जनिमानि विश्वा | शतं मा पुर आयसीररक्षन्नधः श्येनो जवसा निरदीयम् ||२.१.५||",
      "transliteration": "tad uktam ṛṣiṇā | garbhe nu sann anv eṣām avedam ahaṃ devānāṃ janimāni viśvā | śataṃ mā pura āyasīr arakṣann adhaḥ śyeno javasā niradīyam ||2.1.5||",
      "word_meanings": [
        {
          "word": "गर्भे नु सन्",
          "meaning": "while still in the womb"
        },
        {
          "word": "अन्वेषाम् अवेदम्",
          "meaning": "I knew all these"
        },
        {
          "word": "देवानाम् जनिमानि",
          "meaning": "the births of the gods"
        },
        {
          "word": "शतम् पुराः",
          "meaning": "a hundred iron fortresses"
        },
        {
          "word": "श्येनः जवसा",
          "meaning": "like a hawk with speed"
        }
      ],
      "english_translation": "This was said by the seer: 'While still in the womb, I knew all the births of the gods. A hundred iron fortresses held me; then like a hawk with speed I flew down.'",
      "shankara_bhashya_sanskrit": "वामदेवः — गर्भे एव — ज्ञानम् प्राप्तवान्। शतम् पुराः — शरीरम् — आयसीः — दृढाः। श्येनः इव — निरदीयम् — मुक्तः अभवत्।",
      "shankara_bhashya_english": "Shankara: The sage Vamadeva attained knowledge even in the womb. The 'hundred iron fortresses' represent the body and its limitations. Like a hawk breaking free, he attained liberation. This shows that knowledge of the Self can be attained at any stage of life."
    },
    {
      "upanishad": "aitareya",
      "verse_number": 19,
      "tags": [
        "consciousness",
        "all beings",
        "Brahman",
        "prajnanam"
      ],
      "sanskrit": "प्रज्ञेनैव पश्यति प्रज्ञेन शृणोति | प्रज्ञेन गन्धान् जिघ्रति प्रज्ञेन वाचं वदति ||३.१.२||",
      "transliteration": "prajñenaiva paśyati prajñena śṛṇoti | prajñena gandhān jighrati prajñena vācaṃ vadati ||3.1.2||",
      "word_meanings": [
        {
          "word": "प्रज्ञेन पश्यति",
          "meaning": "by consciousness one sees"
        },
        {
          "word": "प्रज्ञेन शृणोति",
          "meaning": "by consciousness one hears"
        },
        {
          "word": "प्रज्ञेन जिघ्रति",
          "meaning": "by consciousness one smells"
        },
        {
          "word": "प्रज्ञेन वदति",
          "meaning": "by consciousness one speaks"
        }
      ],
      "english_translation": "By consciousness alone one sees, by consciousness one hears, by consciousness one smells fragrances, by consciousness one speaks.",
      "shankara_bhashya_sanskrit": "प्रज्ञेन — चैतन्येन — सर्वाणि इन्द्रियाणि प्रवर्तन्ते। चैतन्यम् एव सर्वस्य प्रवर्तकम्।",
      "shankara_bhashya_english": "Shankara: All the senses function by consciousness alone. Consciousness is the activator of everything. Without consciousness, no sense organ can function. This leads to the conclusion: consciousness (prajna) is Brahman."
    },
    {
      "upanishad": "aitareya",
      "verse_number": 20,
      "tags": [
        "consciousness",
        "heart",
        "Brahman",
        "all worlds"
      ],
      "sanskrit": "हृदयं वा इदं ब्रह्म | एतद्ब्रह्म | एतत्सर्वम् ||३.१.३||",
      "transliteration": "hṛdayaṃ vā idaṃ brahma | etad brahma | etat sarvam ||3.1.3||",
      "word_meanings": [
        {
          "word": "हृदयम् इदम् ब्रह्म",
          "meaning": "this heart is Brahman"
        },
        {
          "word": "एतत् ब्रह्म",
          "meaning": "this is Brahman"
        },
        {
          "word": "एतत् सर्वम्",
          "meaning": "this is all"
        }
      ],
      "english_translation": "This heart is indeed Brahman. This is Brahman. This is all.",
      "shankara_bhashya_sanskrit": "हृदयम् — चित्तम् — ब्रह्म। एतत् सर्वम् — सर्वम् ब्रह्मैव।",
      "shankara_bhashya_english": "Shankara: The heart (hridaya) — the seat of consciousness — is Brahman. This is Brahman. This is all. The Aitareya concludes with the simplest and most direct statement: everything is Brahman, and Brahman is consciousness."
    },
    {
      "upanishad": "aitareya",
      "verse_number": 21,
      "tags": [
        "creation",
        "sky",
        "earth",
        "waters"
      ],
      "sanskrit": "स ईक्षत | लोकाः किं नु मे लोकपालान् सृजेयमिति ||१.१.१||",
      "transliteration": "sa īkṣata | lokāḥ kiṃ nu me lokapālān sṛjeyam iti ||1.1.1||",
      "word_meanings": [
        {
          "word": "स ईक्षत",
          "meaning": "he thought/willed"
        },
        {
          "word": "लोकाः",
          "meaning": "worlds"
        },
        {
          "word": "लोकपालान् सृजेयम्",
          "meaning": "let me create guardians of the worlds"
        }
      ],
      "english_translation": "He thought: 'These are the worlds. Let me create guardians of the worlds.'",
      "shankara_bhashya_sanskrit": "स — परमात्मा — ईक्षत — संकल्पम् अकरोत्। लोकपालान् — लोकरक्षकान् — सृजेयम्।",
      "shankara_bhashya_english": "Shankara: The Self willed to create guardians for the worlds it had created. This shows that creation proceeds from the Self's own will and consciousness — not from any external compulsion."
    },
    {
      "upanishad": "aitareya",
      "verse_number": 22,
      "tags": [
        "speech",
        "fire",
        "Agni",
        "creation",
        "organs"
      ],
      "sanskrit": "मुखं निरभिद्यत यथाण्डं मुखाद्वाग्वाचोऽग्निः ||१.१.४||",
      "transliteration": "mukhaṃ nirabhidyata yathāṇḍaṃ mukhād vāg vāco'gniḥ ||1.1.4||",
      "word_meanings": [
        {
          "word": "मुखम् निरभिद्यत",
          "meaning": "the mouth burst open"
        },
        {
          "word": "यथा अण्डम्",
          "meaning": "like an egg"
        },
        {
          "word": "मुखात् वाक्",
          "meaning": "from the mouth, speech"
        },
        {
          "word": "वाचः अग्निः",
          "meaning": "from speech, fire"
        }
      ],
      "english_translation": "The mouth burst open as an egg bursts. From the mouth came speech; from speech, fire.",
      "shankara_bhashya_sanskrit": "मुखम् — वाग्द्वारम् — निरभिद्यत। मुखात् वाक् — वाचः अग्निः — वाग्देवता।",
      "shankara_bhashya_english": "Shankara: The mouth burst open and speech emerged. The deity of speech is Agni (fire). Each organ of the cosmic body has a corresponding cosmic deity — this is the correspondence between microcosm and macrocosm."
    },
    {
      "upanishad": "aitareya",
      "verse_number": 23,
      "tags": [
        "nostrils",
        "prana",
        "Vayu",
        "creation"
      ],
      "sanskrit": "नासिके निरभिद्येतां नासिकाभ्यां प्राणः प्राणाद्वायुः ||१.१.४||",
      "transliteration": "nāsike nirabhidyetāṃ nāsikābhyāṃ prāṇaḥ prāṇād vāyuḥ ||1.1.4||",
      "word_meanings": [
        {
          "word": "नासिके निरभिद्येताम्",
          "meaning": "the two nostrils burst open"
        },
        {
          "word": "नासिकाभ्याम् प्राणः",
          "meaning": "from the nostrils, prana"
        },
        {
          "word": "प्राणात् वायुः",
          "meaning": "from prana, Vayu"
        }
      ],
      "english_translation": "The two nostrils burst open. From the nostrils came prana; from prana, Vayu.",
      "shankara_bhashya_sanskrit": "नासिकाभ्याम् — प्राणः — वायुः। प्राणस्य देवता वायुः।",
      "shankara_bhashya_english": "Shankara: From the nostrils came prana, and the deity of prana is Vayu (wind). The nostrils are the gateway of the life-force in the body."
    },
    {
      "upanishad": "aitareya",
      "verse_number": 24,
      "tags": [
        "eyes",
        "sight",
        "sun",
        "creation"
      ],
      "sanskrit": "अक्षिणी निरभिद्येतामक्षिभ्यां चक्षुश्चक्षुष आदित्यः ||१.१.४||",
      "transliteration": "akṣiṇī nirabhidyetām akṣibhyāṃ cakṣuś cakṣuṣa ādityaḥ ||1.1.4||",
      "word_meanings": [
        {
          "word": "अक्षिणी निरभिद्येताम्",
          "meaning": "the two eyes burst open"
        },
        {
          "word": "अक्षिभ्याम् चक्षुः",
          "meaning": "from the eyes, sight"
        },
        {
          "word": "चक्षुषः आदित्यः",
          "meaning": "from sight, the Sun"
        }
      ],
      "english_translation": "The two eyes burst open. From the eyes came sight; from sight, the Sun.",
      "shankara_bhashya_sanskrit": "अक्षिभ्याम् — चक्षुः — आदित्यः। चक्षुषः देवता आदित्यः।",
      "shankara_bhashya_english": "Shankara: From the eyes came sight, and the deity of sight is the Sun (Aditya). The sun illumines the external world just as the eye perceives it — they are cosmic counterparts."
    },
    {
      "upanishad": "aitareya",
      "verse_number": 25,
      "tags": [
        "ears",
        "hearing",
        "directions",
        "creation"
      ],
      "sanskrit": "कर्णौ निरभिद्येतां कर्णाभ्यां श्रोत्रं श्रोत्राद्दिशः ||१.१.४||",
      "transliteration": "karṇau nirabhidyetāṃ karṇābhyāṃ śrotraṃ śrotrād diśaḥ ||1.1.4||",
      "word_meanings": [
        {
          "word": "कर्णौ निरभिद्येताम्",
          "meaning": "the two ears burst open"
        },
        {
          "word": "कर्णाभ्याम् श्रोत्रम्",
          "meaning": "from the ears, hearing"
        },
        {
          "word": "श्रोत्रात् दिशः",
          "meaning": "from hearing, the directions"
        }
      ],
      "english_translation": "The two ears burst open. From the ears came hearing; from hearing, the directions.",
      "shankara_bhashya_sanskrit": "कर्णाभ्याम् — श्रोत्रम् — दिशः। श्रोत्रस्य देवताः दिशः।",
      "shankara_bhashya_english": "Shankara: From the ears came hearing, and the deities of hearing are the directions (disha). Sound travels in all directions, and the ears receive sound from all directions — hence the correspondence."
    },
    {
      "upanishad": "aitareya",
      "verse_number": 26,
      "tags": [
        "skin",
        "hair",
        "plants",
        "creation"
      ],
      "sanskrit": "त्वङ्निरभिद्यत त्वचो लोमानि लोमभ्य ओषधिवनस्पतयः ||१.१.४||",
      "transliteration": "tvaṅ nirabhidyata tvaco lomāni lomabhya oṣadhivanaspatayaḥ ||1.1.4||",
      "word_meanings": [
        {
          "word": "त्वक् निरभिद्यत",
          "meaning": "the skin burst open"
        },
        {
          "word": "त्वचः लोमानि",
          "meaning": "from the skin, hair"
        },
        {
          "word": "लोमभ्यः ओषधिवनस्पतयः",
          "meaning": "from hair, plants and trees"
        }
      ],
      "english_translation": "The skin burst open. From the skin came hair; from hair, plants and trees.",
      "shankara_bhashya_sanskrit": "त्वचः — लोमानि — ओषधिवनस्पतयः। त्वचः देवताः ओषधयः।",
      "shankara_bhashya_english": "Shankara: From the skin came hair, and the deities of hair are plants and trees. Just as hair grows from the skin, plants grow from the earth. The microcosm (body) mirrors the macrocosm (universe)."
    },
    {
      "upanishad": "aitareya",
      "verse_number": 27,
      "tags": [
        "heart",
        "mind",
        "moon",
        "creation"
      ],
      "sanskrit": "हृदयं निरभिद्यत हृदयान्मनो मनसश्चन्द्रमाः ||१.१.४||",
      "transliteration": "hṛdayaṃ nirabhidyata hṛdayān mano manasaś candramāḥ ||1.1.4||",
      "word_meanings": [
        {
          "word": "हृदयम् निरभिद्यत",
          "meaning": "the heart burst open"
        },
        {
          "word": "हृदयात् मनः",
          "meaning": "from the heart, mind"
        },
        {
          "word": "मनसः चन्द्रमाः",
          "meaning": "from mind, the Moon"
        }
      ],
      "english_translation": "The heart burst open. From the heart came mind; from mind, the Moon.",
      "shankara_bhashya_sanskrit": "हृदयात् — मनः — चन्द्रमाः। मनसः देवता चन्द्रमाः।",
      "shankara_bhashya_english": "Shankara: From the heart came mind, and the deity of mind is the Moon. The moon governs the mind — this is why the mind is said to wax and wane like the moon, and why the full moon affects mental states."
    },
    {
      "upanishad": "aitareya",
      "verse_number": 28,
      "tags": [
        "navel",
        "apana",
        "death",
        "creation"
      ],
      "sanskrit": "नाभिर्निरभिद्यत नाभ्या अपानोऽपानान्मृत्युः ||१.१.४||",
      "transliteration": "nābhir nirabhidyata nābhyā apāno'pānān mṛtyuḥ ||1.1.4||",
      "word_meanings": [
        {
          "word": "नाभिः निरभिद्यत",
          "meaning": "the navel burst open"
        },
        {
          "word": "नाभ्याः अपानः",
          "meaning": "from the navel, apana"
        },
        {
          "word": "अपानात् मृत्युः",
          "meaning": "from apana, death"
        }
      ],
      "english_translation": "The navel burst open. From the navel came apana; from apana, death.",
      "shankara_bhashya_sanskrit": "नाभ्याः — अपानः — मृत्युः। अपानस्य देवता मृत्युः।",
      "shankara_bhashya_english": "Shankara: From the navel came apana (the downward breath), and the deity of apana is death (Mrityu). Apana governs elimination and the downward movement of energy — associated with the process of dying."
    },
    {
      "upanishad": "aitareya",
      "verse_number": 29,
      "tags": [
        "generative organ",
        "water",
        "creation",
        "Varuna"
      ],
      "sanskrit": "शिश्नं निरभिद्यत शिश्नाद्रेतो रेतस आपः ||१.१.४||",
      "transliteration": "śiśnaṃ nirabhidyata śiśnād reto retasa āpaḥ ||1.1.4||",
      "word_meanings": [
        {
          "word": "शिश्नम् निरभिद्यत",
          "meaning": "the generative organ burst open"
        },
        {
          "word": "शिश्नात् रेतः",
          "meaning": "from it, seed"
        },
        {
          "word": "रेतसः आपः",
          "meaning": "from seed, waters"
        }
      ],
      "english_translation": "The generative organ burst open. From it came seed; from seed, the waters.",
      "shankara_bhashya_sanskrit": "शिश्नात् — रेतः — आपः। रेतसः देवताः आपः।",
      "shankara_bhashya_english": "Shankara: From the generative organ came seed, and the deity of seed is water (Apas). Water is the cosmic counterpart of the generative principle — both are associated with fertility and creation."
    },
    {
      "upanishad": "aitareya",
      "verse_number": 30,
      "tags": [
        "deities",
        "entered body",
        "hunger",
        "thirst",
        "fire"
      ],
      "sanskrit": "ता एता देवताः सृष्टा अस्मिन्महत्यर्णवे प्रापतन् | तमशनायापिपासाभ्यामन्ववार्जत् ||१.२.१||",
      "transliteration": "tā etā devatāḥ sṛṣṭā asmin mahaty arṇave prāpatan | tam aśanāyāpipāsābhyām anvavārjat ||1.2.1||",
      "word_meanings": [
        {
          "word": "देवताः सृष्टाः",
          "meaning": "the created deities"
        },
        {
          "word": "महति अर्णवे प्रापतन्",
          "meaning": "fell into the great ocean"
        },
        {
          "word": "अशनाया अपिपासाभ्याम्",
          "meaning": "by hunger and thirst"
        },
        {
          "word": "अन्ववार्जत्",
          "meaning": "were overcome"
        }
      ],
      "english_translation": "These created deities fell into the great ocean. Hunger and thirst overcame him.",
      "shankara_bhashya_sanskrit": "देवताः — वाग्आदयः — संसारसागरे प्रापतन्। अशनाया अपिपासाभ्याम् — क्षुत्पिपासाभ्याम् — अन्ववार्जत्।",
      "shankara_bhashya_english": "Shankara: The created deities fell into the ocean of samsara. The cosmic person was overcome by hunger and thirst — the fundamental drives of embodied existence. This sets up the need for food (the objective world) to be created."
    },
    {
      "upanishad": "aitareya",
      "verse_number": 31,
      "tags": [
        "deities",
        "entered body",
        "fire",
        "speech",
        "mouth"
      ],
      "sanskrit": "ता अब्रुवन् | अधि नो ब्रूहि यस्मिन् प्रतिष्ठिताः अन्नमदाम ||१.२.३||",
      "transliteration": "tā abruvan | adhi no brūhi yasmin pratiṣṭhitāḥ annam adāma ||1.2.3||",
      "word_meanings": [
        {
          "word": "अधि नः ब्रूहि",
          "meaning": "tell us"
        },
        {
          "word": "यस्मिन् प्रतिष्ठिताः",
          "meaning": "in which established"
        },
        {
          "word": "अन्नम् अदाम",
          "meaning": "we may eat food"
        }
      ],
      "english_translation": "They said: 'Tell us — established in which, may we eat food?'",
      "shankara_bhashya_sanskrit": "देवताः अपृच्छन् — कस्मिन् शरीरे प्रतिष्ठिताः — अन्नम् अदाम — भोगम् प्राप्नुयाम।",
      "shankara_bhashya_english": "Shankara: The deities asked to be placed in a body so they could experience the world. They needed a vehicle (body) to enjoy food and experience existence. This leads to the Self entering the body."
    },
    {
      "upanishad": "aitareya",
      "verse_number": 32,
      "tags": [
        "Self",
        "entered body",
        "cow",
        "horse",
        "person"
      ],
      "sanskrit": "तासां गां दर्शयामास | ता अब्रुवन् न वै नोऽयमलमिति | अश्वं दर्शयामास | ता अब्रुवन् न वै नोऽयमलमिति | पुरुषं दर्शयामास | ता अब्रुवन् सुकृतं बतेति | पुरुषो वाव सुकृतम् ||१.२.३||",
      "transliteration": "tāsāṃ gāṃ darśayām āsa | tā abruvan na vai no'yam alam iti | aśvaṃ darśayām āsa | tā abruvan na vai no'yam alam iti | puruṣaṃ darśayām āsa | tā abruvan sukṛtaṃ bateti | puruṣo vāva sukṛtam ||1.2.3||",
      "word_meanings": [
        {
          "word": "गाम् दर्शयामास",
          "meaning": "showed them a cow"
        },
        {
          "word": "न अयम् अलम्",
          "meaning": "this is not enough for us"
        },
        {
          "word": "पुरुषम् दर्शयामास",
          "meaning": "showed them a person"
        },
        {
          "word": "सुकृतम् बत",
          "meaning": "well made indeed"
        },
        {
          "word": "पुरुषः सुकृतम्",
          "meaning": "the person is well made"
        }
      ],
      "english_translation": "He showed them a cow. They said: 'This is not enough for us.' He showed them a horse. They said: 'This is not enough.' He showed them a person. They said: 'Well made indeed!' The person is indeed well made.",
      "shankara_bhashya_sanskrit": "गाम् — अश्वम् — पुरुषम् — दर्शयामास। पुरुषः — सुकृतम् — सर्वेन्द्रियसम्पन्नः।",
      "shankara_bhashya_english": "Shankara: The deities rejected the cow and horse as insufficient vehicles. They chose the human body as the best — 'well made' — because it has all the organs needed for full experience and, most importantly, for self-knowledge. The human body is the best vehicle for liberation."
    },
    {
      "upanishad": "aitareya",
      "verse_number": 33,
      "tags": [
        "Self",
        "entered body",
        "brahmarandhra",
        "three births",
        "liberation"
      ],
      "sanskrit": "स एतमेव सीमानं विदार्यैतया द्वारा प्रापद्यत | सैषा विदृतिर्नाम द्वास्तदेतन्नान्दनं नाम ||१.३.१२||",
      "transliteration": "sa etam eva sīmānam vidāryaitayā dvārā prāpadyata | saiṣā vidṛtir nāma dvās tad etan nāndanaṃ nāma ||1.3.12||",
      "word_meanings": [
        {
          "word": "सीमानम् विदार्य",
          "meaning": "splitting the crown of the head"
        },
        {
          "word": "एतया द्वारा प्रापद्यत",
          "meaning": "entered by this door"
        },
        {
          "word": "विदृतिः नाम द्वाः",
          "meaning": "the door called Vidrti"
        },
        {
          "word": "नान्दनम् नाम",
          "meaning": "called Nandana (joy)"
        }
      ],
      "english_translation": "Splitting the crown of the head, it entered by this door. This door is called Vidrti. This is the place called Nandana.",
      "shankara_bhashya_sanskrit": "सीमानम् विदार्य — ब्रह्मरन्ध्रम् भित्त्वा — प्रविशत्। विदृतिः — ब्रह्मरन्ध्रम् — नान्दनम् — आनन्दस्थानम्।",
      "shankara_bhashya_english": "Shankara: The Self entered the cosmic body through the crown of the head (brahmarandhra). This is called Vidrti (the cleft) and Nandana (the place of joy) — because the Self's entry brings consciousness and bliss to the body. At death, the liberated soul exits through this same door."
    }
  ]
}